shapi/__init__.py
shapi/cli.py
shapi/core.py
shapi/exceptions.py
shapi/generator.py
shapi/protocols/__init__.py
shapi/protocols/grpc.py
shapi/protocols/rest.py
shapi/protocols/webrtc.py
shapi/service_manager.py
shapi/templates.py
shapi-0.2.14.dist-info/LICENSE
shapi-0.2.14.dist-info/METADATA
shapi-0.2.14.dist-info/WHEEL
shapi-0.2.14.dist-info/entry_points.txt
shapi-0.2.14.dist-info/RECORD
