Metadata-Version: 2.3
Name: shapi
Version: 0.2.14
Summary: Transform shell scripts into production-ready APIs with REST, WebRTC, and gRPC support
License: Apache-2.0
Author: Tom Sapletta
Author-email: info@softreck.dev
Requires-Python: >=3.9,<4.0
Classifier: Development Status :: 3 - Alpha
Classifier: Intended Audience :: Developers
Classifier: Intended Audience :: System Administrators
Classifier: License :: OSI Approved :: Apache Software License
Classifier: Programming Language :: Python :: 3
Classifier: Programming Language :: Python :: 3.9
Classifier: Programming Language :: Python :: 3.10
Classifier: Programming Language :: Python :: 3.11
Classifier: Programming Language :: Python :: 3.12
Classifier: Programming Language :: Python :: 3.13
Classifier: Topic :: Software Development :: Code Generators
Classifier: Topic :: Software Development :: Libraries :: Application Frameworks
Classifier: Topic :: System :: Systems Administration
Classifier: Topic :: Utilities
Provides-Extra: all
Provides-Extra: cli
Provides-Extra: server
Requires-Dist: click (>=8.1.7,<9.0.0)
Requires-Dist: fastapi (>=0.104.0,<0.105.0) ; extra == "server" or extra == "all"
Requires-Dist: lxml (>=5.1.0,<6.0.0) ; extra == "all"
Requires-Dist: openai (>=1.3.0,<2.0.0) ; extra == "all"
Requires-Dist: pydantic (>=2.5.0,<3.0.0)
Requires-Dist: pypdf (>=3.17.0,<4.0.0) ; extra == "all"
Requires-Dist: python-docx (>=1.1.0,<2.0.0) ; extra == "all"
Requires-Dist: python-multipart (>=0.0.6,<0.0.7) ; extra == "server" or extra == "all"
Requires-Dist: pyyaml (>=6.0.1,<7.0.0)
Requires-Dist: requests (>=2.31.0,<3.0.0)
Requires-Dist: rich-click (>=1.7.0,<2.0.0) ; extra == "cli" or extra == "all"
Requires-Dist: rich[all] (>=13.0.0,<14.0.0)
Requires-Dist: uvicorn (>=0.24.0,<0.25.0) ; extra == "server" or extra == "all"
Project-URL: Bug Tracker, https://github.com/wronai/shapi/issues
Project-URL: Changelog, https://github.com/wronai/shapi/blob/main/CHANGELOG.md
Project-URL: Documentation, https://wronai.github.io/shapi
Project-URL: Homepage, https://github.com/wronai/shapi
Project-URL: Repository, https://github.com/wronai/shapi
Project-URL: Source Code, https://github.com/wronai/shapi
